Loss/__init__.py
Loss/AngularPenaltySMLoss/AngularPenaltySMLoss.py
Loss/AngularPenaltySMLoss/__init__.py
Loss/SmoothingLabel/SmoothingLabel.py
Loss/SmoothingLabel/__init__.py
Models/__init__.py
Models/Classification/__init__.py
Models/Classification/ResNest/__init__.py
Models/Classification/ResNest/resnest.py
Models/Classification/ResNest/resnet.py
Models/Classification/ResNest/splat.py
Models/Classification/SENet/SENet.py
Models/Classification/SENet/__init__.py
syyDlib-0.0.6.dist-info/LICENSE
syyDlib-0.0.6.dist-info/METADATA
syyDlib-0.0.6.dist-info/WHEEL
syyDlib-0.0.6.dist-info/top_level.txt
syyDlib-0.0.6.dist-info/RECORD
