Metadata-Version: 2.1
Name: syyDlib
Version: 0.0.6
Summary: for test
Home-page: UNKNOWN
Author: Jay
Author-email: UNKNOWN
License: UNKNOWN
Platform: UNKNOWN
